haystack_integrations/components/embedders/py.typed
haystack_integrations/components/embedders/ollama/__init__.py
haystack_integrations/components/embedders/ollama/document_embedder.py
haystack_integrations/components/embedders/ollama/text_embedder.py
haystack_integrations/components/generators/py.typed
haystack_integrations/components/generators/ollama/__init__.py
haystack_integrations/components/generators/ollama/generator.py
haystack_integrations/components/generators/ollama/chat/__init__.py
haystack_integrations/components/generators/ollama/chat/chat_generator.py
ollama_haystack-5.3.0.dist-info/METADATA
ollama_haystack-5.3.0.dist-info/WHEEL
ollama_haystack-5.3.0.dist-info/licenses/LICENSE.txt
ollama_haystack-5.3.0.dist-info/RECORD
