Metadata-Version: 2.4
Name: ollama-haystack
Version: 5.3.0
Summary: An integration between the Ollama LLM framework and Haystack
Project-URL: Documentation, https://github.com/deepset-ai/haystack-core-integrations/tree/main/integrations/ollama#readme
Project-URL: Issues, https://github.com/deepset-ai/haystack-core-integrations/issues
Project-URL: Source, https://github.com/deepset-ai/haystack-core-integrations/tree/main/integrations/ollama
Author-email: Alistair Rogers <alistairlr112@gmail.com>, Sachin Sachdeva <emailforsachinsachdeva@gmail.com>, deepset GmbH <info@deepset.ai>
License-Expression: Apache-2.0
License-File: LICENSE.txt
Classifier: Development Status :: 4 - Beta
Classifier: License :: OSI Approved :: Apache Software License
Classifier: Programming Language :: Python
Classifier: Programming Language :: Python :: 3.9
Classifier: Programming Language :: Python :: 3.10
Classifier: Programming Language :: Python :: 3.11
Classifier: Programming Language :: Python :: 3.12
Classifier: Programming Language :: Python :: 3.13
Classifier: Programming Language :: Python :: Implementation :: CPython
Classifier: Programming Language :: Python :: Implementation :: PyPy
Requires-Python: >=3.9
Requires-Dist: haystack-ai>=2.19.0
Requires-Dist: ollama>=0.5.0
Requires-Dist: pydantic
